alauda_kombu-3.0.38.dist-info/METADATA
alauda_kombu-3.0.38.dist-info/RECORD
alauda_kombu-3.0.38.dist-info/WHEEL
alauda_kombu-3.0.38.dist-info/top_level.txt
kombu/__init__.py
kombu/abstract.py
kombu/clocks.py
kombu/common.py
kombu/compat.py
kombu/compression.py
kombu/connection.py
kombu/entity.py
kombu/exceptions.py
kombu/five.py
kombu/log.py
kombu/message.py
kombu/messaging.py
kombu/mixins.py
kombu/pidbox.py
kombu/pools.py
kombu/serialization.py
kombu/simple.py
kombu/syn.py
kombu/async/__init__.py
kombu/async/debug.py
kombu/async/hub.py
kombu/async/semaphore.py
kombu/async/timer.py
kombu/tests/__init__.py
kombu/tests/case.py
kombu/tests/mocks.py
kombu/tests/test_clocks.py
kombu/tests/test_common.py
kombu/tests/test_compat.py
kombu/tests/test_compression.py
kombu/tests/test_connection.py
kombu/tests/test_entities.py
kombu/tests/test_log.py
kombu/tests/test_messaging.py
kombu/tests/test_mixins.py
kombu/tests/test_pidbox.py
kombu/tests/test_pools.py
kombu/tests/test_serialization.py
kombu/tests/test_simple.py
kombu/tests/test_syn.py
kombu/tests/async/__init__.py
kombu/tests/async/test_hub.py
kombu/tests/async/test_semaphore.py
kombu/tests/transport/__init__.py
kombu/tests/transport/test_SQS.py
kombu/tests/transport/test_amqplib.py
kombu/tests/transport/test_base.py
kombu/tests/transport/test_filesystem.py
kombu/tests/transport/test_librabbitmq.py
kombu/tests/transport/test_memory.py
kombu/tests/transport/test_mongodb.py
kombu/tests/transport/test_pyamqp.py
kombu/tests/transport/test_qpid.py
kombu/tests/transport/test_redis.py
kombu/tests/transport/test_redis_cluster.py
kombu/tests/transport/test_sqlalchemy.py
kombu/tests/transport/test_transport.py
kombu/tests/transport/virtual/__init__.py
kombu/tests/transport/virtual/test_base.py
kombu/tests/transport/virtual/test_exchange.py
kombu/tests/transport/virtual/test_scheduling.py
kombu/tests/utils/__init__.py
kombu/tests/utils/test_amq_manager.py
kombu/tests/utils/test_debug.py
kombu/tests/utils/test_encoding.py
kombu/tests/utils/test_functional.py
kombu/tests/utils/test_utils.py
kombu/transport/SLMQ.py
