Metadata-Version: 2.1
Name: alauda-kombu
Version: 3.0.38
Summary: Messaging library for Python
Home-page: https://kombu.readthedocs.io
Author: Ask Solem
Author-email: ask@celeryproject.org
License: UNKNOWN
Platform: any
Classifier: Development Status :: 5 - Production/Stable
Classifier: License :: OSI Approved :: BSD License
Classifier: Operating System :: OS Independent
Classifier: Programming Language :: Python
Classifier: Programming Language :: Python :: 3
Classifier: Programming Language :: Python :: 3.4
Classifier: Programming Language :: Python :: 3.3
Classifier: Programming Language :: Python :: 2.7
Classifier: Programming Language :: Python :: 2.6
Classifier: Programming Language :: Python :: 2
Classifier: Programming Language :: Python :: Implementation :: CPython
Classifier: Programming Language :: Python :: Implementation :: PyPy
Classifier: Programming Language :: Python :: Implementation :: Jython
Classifier: Intended Audience :: Developers
Classifier: Topic :: Communications
Classifier: Topic :: System :: Distributed Computing
Classifier: Topic :: System :: Networking
Classifier: Topic :: Software Development :: Libraries :: Python Modules
Provides-Extra: qpid
Provides-Extra: redis-cluster
Provides-Extra: sqlalchemy
Provides-Extra: yaml
Provides-Extra: librabbitmq
Provides-Extra: mongodb
Provides-Extra: zookeeper
Provides-Extra: redis
Provides-Extra: pyro
Provides-Extra: sqs
Provides-Extra: beanstalk
Provides-Extra: slmq
Provides-Extra: msgpack
Provides-Extra: zeromq
Provides-Extra: couchdb
Requires-Dist: anyjson (>=0.3.3)
Requires-Dist: amqp (<2.0,>=1.4.9)
Requires-Dist: importlib; python_version=="2.6"
Requires-Dist: ordereddict; python_version=="2.6"
Provides-Extra: beanstalk
Requires-Dist: beanstalkc; extra == 'beanstalk'
Provides-Extra: couchdb
Requires-Dist: couchdb; extra == 'couchdb'
Provides-Extra: librabbitmq
Requires-Dist: librabbitmq (>=1.6.1); extra == 'librabbitmq'
Provides-Extra: mongodb
Requires-Dist: pymongo (>=2.6.2); extra == 'mongodb'
Provides-Extra: msgpack
Requires-Dist: msgpack-python (>=0.4.7); extra == 'msgpack'
Provides-Extra: pyro
Requires-Dist: pyro4; extra == 'pyro'
Provides-Extra: qpid
Requires-Dist: qpid-python (>=0.26); extra == 'qpid'
Requires-Dist: qpid-tools (>=0.26); extra == 'qpid'
Provides-Extra: redis
Requires-Dist: redis (>=2.10.3); extra == 'redis'
Provides-Extra: redis-cluster
Requires-Dist: redis (>=2.10.3); extra == 'redis-cluster'
Requires-Dist: alauda-redis-py-cluster (==1.3.4); extra == 'redis-cluster'
Provides-Extra: slmq
Requires-Dist: softlayer-messaging (>=1.0.3); extra == 'slmq'
Provides-Extra: sqlalchemy
Requires-Dist: sqlalchemy; extra == 'sqlalchemy'
Provides-Extra: sqs
Requires-Dist: boto (>=2.13.3); extra == 'sqs'
Provides-Extra: yaml
Requires-Dist: PyYAML (>=3.10); extra == 'yaml'
Provides-Extra: zeromq
Requires-Dist: pyzmq (>=13.1.0); extra == 'zeromq'
Provides-Extra: zookeeper
Requires-Dist: kazoo (>=1.3.1); extra == 'zookeeper'
